i18nTool/__init__.py
i18nTool/copyright.py
i18nTool/flags.py
i18nTool/i18n.py
i18nTool/read.py
i18ntool-0.1.0.dist-info/METADATA
i18ntool-0.1.0.dist-info/WHEEL
i18ntool-0.1.0.dist-info/entry_points.txt
i18ntool-0.1.0.dist-info/licenses/LICENSE
i18ntool-0.1.0.dist-info/RECORD
