Metadata-Version: 2.1
Name: i18nTool
Version: 0.1.0
Summary: A Simple and lightweight Python internationalization (i18n) tool.
Author-Email: weinibuliu <weinibuliu@outlook.com>
License: MIT
Project-URL: Repository, https://github.com/weinibuliu/python-i18nTool
Requires-Python: >=3.9
Requires-Dist: pyyaml
